mathlibtools/__init__.py
mathlibtools/_version.py
mathlibtools/auth_github.py
mathlibtools/decls.lean
mathlibtools/delayed_interrupt.py
mathlibtools/file_status.py
mathlibtools/git_helpers.py
mathlibtools/import_graph.py
mathlibtools/leanproject.py
mathlibtools/lib.py
mathlibtools/new_lib.py
mathlibtools/post-checkout
mathlibtools/post-commit
mathlibtools-1.3.2.dist-info/LICENSE
mathlibtools-1.3.2.dist-info/METADATA
mathlibtools-1.3.2.dist-info/WHEEL
mathlibtools-1.3.2.dist-info/entry_points.txt
mathlibtools-1.3.2.dist-info/top_level.txt
mathlibtools-1.3.2.dist-info/RECORD
