Metadata-Version: 2.1
Name: mathlibtools
Version: 1.3.2
Summary: Lean prover mathlib supporting tools.
Home-page: https://github.com/leanprover-community/mathlib-tools
Author: The mathlib community
Classifier: Programming Language :: Python :: 3
Classifier: License :: OSI Approved :: Apache Software License
Classifier: Operating System :: OS Independent
Requires-Python: >=3.6
License-File: LICENSE
Requires-Dist: toml (>=0.10.0)
Requires-Dist: PyGithub
Requires-Dist: certifi
Requires-Dist: gitpython (>=2.1.11)
Requires-Dist: requests
Requires-Dist: Click
Requires-Dist: tqdm
Requires-Dist: networkx
Requires-Dist: pydot
Requires-Dist: PyYAML (>=3.13)
Requires-Dist: atomicwrites
Requires-Dist: dataclasses ; python_version == "3.6"
